chalkdf-3.30.4.dist-info/RECORD
chalkdf-3.30.4.dist-info/WHEEL
chalkdf-3.30.4.dist-info/entry_points.txt
chalkdf-3.30.4.dist-info/top_level.txt
chalkdf-3.30.4.dist-info/METADATA
chalkdf/libchalk.cpython-310-darwin.so
chalkdf/_chalk_import.py
chalkdf/_libchalk_bootstrap.py
chalkdf/config.py
chalkdf/_metaclass.py
chalkdf/util.py
chalkdf/dataframe.py
chalkdf/__init__.py
chalkdf/_display.py
chalkdf/lazyframe.py
chalkdf/debug.py
chalkdf/sql.py
chalkdf/testing.py
chalkdf/schema.py
chalkdf/underscore_conversion/convert_underscore_to_expr.py
chalkdf/underscore_conversion/__init__.py
_chalk_shared_public/arrow_type_promotion.py
_chalk_shared_public/__init__.py
_chalk_shared_public/py.typed
_chalk_shared_public/chalk_function_registry.py
