Metadata-Version: 2.4
Name: chalkdf
Version: 3.30.4
Summary: DataFrame utilities for Chalk AI, backed by libchalk
Author-email: "Chalk AI, Inc." <opensource@chalk.ai>
Project-URL: Homepage, https://chalk.ai
Project-URL: Documentation, https://docs.chalk.ai
Project-URL: Changelog, https://docs.chalk.ai/docs/changelog
Requires-Python: <=3.14,>=3.10
Requires-Dist: frozendict>=2.4.6
Requires-Dist: python-dateutil>=2.8.2
Requires-Dist: pyarrow>=18.0.0
Requires-Dist: ddtrace<3,>=2.6.4
Provides-Extra: chalkpy
Requires-Dist: chalkpy[athena,bigquery,databricks,mysql,postgresql,redshift,snowflake,spanner,sqlite,trino]>=2.93.8; extra == "chalkpy"
Provides-Extra: dev
Requires-Dist: ruff; extra == "dev"
Requires-Dist: pytest; extra == "dev"
Requires-Dist: pytest-cov; extra == "dev"
Requires-Dist: build; extra == "dev"
Requires-Dist: google-cloud-storage>=3; extra == "dev"
Requires-Dist: polars; extra == "dev"
Requires-Dist: setuptools>=65; extra == "dev"
Requires-Dist: flaky>=3.8.1; extra == "dev"
Requires-Dist: chalkpy[athena,bigquery,databricks,mysql,postgresql,redshift,snowflake,spanner,sqlite,trino]>=2.89.5; extra == "dev"
Provides-Extra: bench
Requires-Dist: google-cloud-storage>=3; extra == "bench"
Requires-Dist: polars; extra == "bench"
Requires-Dist: setuptools>=65; extra == "bench"
